kedro_mcp/__init__.py
kedro_mcp/server.py
kedro_mcp/prompts/kedro_general_instructions.md
kedro_mcp/prompts/migration.md
kedro_mcp/prompts/notebook_to_kedro.md
kedro_mcp-0.1.2.dist-info/licenses/LICENSE.txt
kedro_mcp-0.1.2.dist-info/METADATA
kedro_mcp-0.1.2.dist-info/WHEEL
kedro_mcp-0.1.2.dist-info/entry_points.txt
kedro_mcp-0.1.2.dist-info/top_level.txt
kedro_mcp-0.1.2.dist-info/RECORD
