Metadata-Version: 2.4
Name: kedro-mcp
Version: 0.1.2
Summary: MCP server with Kedro prompts and tools (local stdio, zero-install via uvx).
Author: Kedro
License:                                  Apache License
Project-URL: Homepage, https://github.com/kedro-org/kedro-mcp
Keywords: Kedro,MCP,Model Context Protocol,GenAI,AI,data science,data engineering
Classifier: Programming Language :: Python
Classifier: Programming Language :: Python :: 3.10
Classifier: Programming Language :: Python :: 3.11
Classifier: Programming Language :: Python :: 3.12
Classifier: Programming Language :: Python :: 3.13
Requires-Python: >=3.10
License-File: LICENSE.txt
Requires-Dist: fastmcp>=0.3
Dynamic: license-file
